card_game_analysis/__init__.py
card_game_analysis/card.py
card_game_analysis/daifugo.py
card_game_analysis/deck.py
card_game_analysis/game.py
card_game_analysis/player.py
card_game_analysis/players.py
card_game_analysis/stack.py
card_game_analysis-0.0.4.dist-info/LICENSE
card_game_analysis-0.0.4.dist-info/METADATA
card_game_analysis-0.0.4.dist-info/WHEEL
card_game_analysis-0.0.4.dist-info/top_level.txt
card_game_analysis-0.0.4.dist-info/RECORD
