Metadata-Version: 2.1
Name: card-game-analysis
Version: 0.0.4
Summary: Tools to analyse card games
Home-page: https://github.com/nwnordahl/card-game-analysis
Author: Nicolai Warenfors Nordahl
Author-email: nicolaiwnordahl@gmail.com
License: UNKNOWN
Project-URL: Documentation, https://card-game-analysis.rtfd.io
Platform: UNKNOWN
Classifier: Programming Language :: Python :: 3
Classifier: License :: OSI Approved :: MIT License
Classifier: Operating System :: OS Independent
Requires-Python: >=3.6
License-File: LICENSE
